media/__init__.py
media/run.py
media/voice.py
media-0.1.6.dist-info/LICENSE
media-0.1.6.dist-info/METADATA
media-0.1.6.dist-info/WHEEL
media-0.1.6.dist-info/entry_points.txt
media-0.1.6.dist-info/top_level.txt
media-0.1.6.dist-info/RECORD
