Metadata-Version: 2.1
Name: media
Version: 0.1.6
Summary: A Media Toolkit. Text-to-speech is currently available.
Home-page: https://ahamega.com/support
Author: leesoar
Author-email: core@111.com
License: MIT
Keywords: media,text-to-speech,azure
Platform: UNKNOWN
Classifier: License :: OSI Approved :: MIT License
Classifier: Programming Language :: Python :: 3.5
Classifier: Programming Language :: Python :: 3.6
Classifier: Programming Language :: Python :: 3.7
Classifier: Programming Language :: Python :: Implementation :: CPython
Classifier: Programming Language :: Python :: Implementation :: PyPy
Requires-Python: >=3.3.0
